gtirb_rewriting/__init__.py
gtirb_rewriting/__main__.py
gtirb_rewriting/_auxdata.py
gtirb_rewriting/_auxdata_offsetmap.py
gtirb_rewriting/abi.py
gtirb_rewriting/assembly.py
gtirb_rewriting/driver.py
gtirb_rewriting/intervalutils.py
gtirb_rewriting/passes.py
gtirb_rewriting/patch.py
gtirb_rewriting/prepare.py
gtirb_rewriting/rewriting.py
gtirb_rewriting/scopes.py
gtirb_rewriting/utils.py
gtirb_rewriting/version.py
gtirb_rewriting/_adt/__init__.py
gtirb_rewriting/_adt/block_ordering.py
gtirb_rewriting/_adt/identity_set.py
gtirb_rewriting/_adt/linked_list.py
gtirb_rewriting/_adt/offset_mapping.py
gtirb_rewriting/_modify/__init__.py
gtirb_rewriting/_modify/cache.py
gtirb_rewriting/_modify/delete_symbols.py
gtirb_rewriting/_modify/edges.py
gtirb_rewriting/_modify/edit.py
gtirb_rewriting/_modify/functions.py
gtirb_rewriting/_modify/join.py
gtirb_rewriting/_modify/remove.py
gtirb_rewriting/_modify/retarget.py
gtirb_rewriting/_modify/split.py
gtirb_rewriting/assembler/__init__.py
gtirb_rewriting/assembler/__main__.py
gtirb_rewriting/assembler/_create_gtirb.py
gtirb_rewriting/assembler/_mc_utils.py
gtirb_rewriting/assembler/assembler.py
gtirb_rewriting/dwarf/__init__.py
gtirb_rewriting/dwarf/_encodable.py
gtirb_rewriting/dwarf/_encoders.py
gtirb_rewriting/dwarf/cfi.py
gtirb_rewriting/dwarf/cfi_eval.py
gtirb_rewriting/dwarf/dwarf2.py
gtirb_rewriting/dwarf/expr.py
gtirb_rewriting/gtirb_protobuf_compat/__init__.py
gtirb_rewriting/gtirb_protobuf_compat/proto_3.py
gtirb_rewriting/gtirb_protobuf_compat/proto_4.py
gtirb_rewriting/patches/__init__.py
gtirb_rewriting/patches/calls.py
gtirb_rewriting-0.3.0.dist-info/LICENSE.txt
gtirb_rewriting-0.3.0.dist-info/METADATA
gtirb_rewriting-0.3.0.dist-info/WHEEL
gtirb_rewriting-0.3.0.dist-info/entry_points.txt
gtirb_rewriting-0.3.0.dist-info/top_level.txt
gtirb_rewriting-0.3.0.dist-info/RECORD
