Metadata-Version: 2.1
Name: gtirb-rewriting
Version: 0.3.0
Summary: Utilities for rewriting GTIRB
Home-page: https://github.com/grammatech/gtirb-rewriting
Author: GrammaTech
Author-email: gtirb@grammatech.com
License: GPLv3
Platform: UNKNOWN
Classifier: Programming Language :: Python :: 3
Requires-Python: >=3.7
License-File: LICENSE.txt
Requires-Dist: capstone-gt
Requires-Dist: gtirb-capstone >=1.0.1
Requires-Dist: gtirb-functions >=1.0.8
Requires-Dist: gtirb-layout ~=1.0
Requires-Dist: gtirb >=1.10.6
Requires-Dist: mcasm ~=0.3.0
Requires-Dist: more-itertools >=8.11
Requires-Dist: entrypoints
Requires-Dist: typing-extensions ~=4.7
Requires-Dist: leb128 >=1.0.2,~=1.0
